arrebol/__init__.py
arrebol/gerador/__init__.py
arrebol/gerador/traquitana.py
arrebol-1.0.18.dist-info/LICENSE
arrebol-1.0.18.dist-info/METADATA
arrebol-1.0.18.dist-info/WHEEL
arrebol-1.0.18.dist-info/top_level.txt
arrebol-1.0.18.dist-info/RECORD
