Metadata-Version: 2.1
Name: arrebol
Version: 1.0.18
Summary: Test Conda
Home-page: https://github.com/traquitanas/arrebol
Author: Michel Metran
Author-email: michelmetran@gmail.com
Keywords: python,endereço aleatorio,address
Classifier: Programming Language :: Python :: 3
Classifier: License :: OSI Approved :: MIT License
Classifier: Operating System :: OS Independent
Classifier: Natural Language :: Portuguese
Classifier: Intended Audience :: Developers
License-File: LICENSE
Requires-Dist: requests (>=2.10.1)
